Workbook
Name RawData: RawData!$A$1:$G$1362
Name RawDataCompany: RawData!$A$2:$A$1362

Sheet TextFunctions
A7: Left
B8: Function
B9: Left | C9: =LEFT(C12,C13) -> NC | D9: Applicable to :
D10: Seperating Names ("Tom Hinkle")
B11: Arguments
B12: Text | C12: NC-1212121
B13: Number | C13: 2
A15: Right
B16: Function
B17: Right | C17: =RIGHT(C20,C21) -> 25251 | D17: Seperating Names ("Tom Hinkle")
B19: Arguments
B20: Text | C20: 2228 Viking Drive, Columbus, OH 25251
B21: Number | C21: 5
A23: Mid
B24: Function
B25: Mid | C25: =MID(C28,C29,C30) -> Columbus | D25: Applicable to
C26: =MID(C28,12,6) -> Drive | D26: Removing a Piece of text from a string
B27: Arguments | D27: (Good to partner with find)
B28: Text | C28: 2228 Viking Drive, Columbus, OH 25251
B29: Start | C29: 20
B30: Num_chars | C30: 8
A32: Len
B33: Function
B34: Len | C34: =LEN(C37) -> 5 | D34: Applicable to
C35: =LEN(D34) -> 13
B36: Arguments
B37: Text | C37: Extra
A39: Find
B40: Function
B41: Find | C41: =FIND(C44,C45,1) -> 13
D42: useful to pull out data from inside a string
B43: Arguments
B44: Find_Text | C44: Drive
B45: Within_Text | C45: 2228 Viking Drive, Columbus, OH 25251 | D45: =FIND(C44,C45,13) -> 13
B46: Start | C46: 0
A48: Trim
B49: Function
B50: Trim | C50: =TRIM(C53) -> This Text Contains a LOT of extra space .
D51: =TRIM(C53) -> This Text Contains a LOT of extra space .
B52: Arguments
B53: Text | C53: This Text Contains a LOT of extra space .
A55: Upper, Lower, Proper Case
C56: ThIS sentEnce HAS all KiNdS of InCONsisTant formatting.
B57: Function
B58: Upper
B59: Lower | D59: =LOWER(C56) -> this sentence has all kinds of inconsistant formatting.
B60: Proper | D60: =PROPER(C56) -> This Sentence Has All Kinds Of Inconsistant Formatting.
D61: =UPPER(C56) -> THIS SENTENCE HAS ALL KINDS OF INCONSISTANT FORMATTING.
B62: Arguments
B63: Text
A65: Concatenate
B66: Function
B67: Concatenate | D67: =CONCATENATE(C71,C72,C73) -> 2228 Viking DriveColumbusOH 25251
B68: Ampersand (&) | C68: =C71&C72&C73 -> 2228 Viking DriveColumbusOH 25251 | D68: =CONCATENATE(C71,C69,C72,C69,C73) -> 2228 Viking Drive Columbus OH 25251
B70: Arguments
B71: Text1 | C71: 2228 Viking Drive
B72: Text2 | C72: Columbus
B73: Text3 | C73: OH 25251
A75: Clean
B76: Function
B77: Clean | C77: =CLEAN(C80) -> This has a non-printable character.Another Line. | D77: =CLEAN(C80) -> This has a non-printable character.Another Line.
B79: Arguments
B80: Text | C80: This has a non-printable character. Another Line.
A82: Exact
B83: Function
B84: Exact | C84: =EXACT(C87,C88) -> TRUE
B86: Arguments | D86: =EXACT(C87,C88) -> TRUE
B87: Text1 | C87: Exact
B88: Text2 | C88: Exact
A90: Value
B91: Function
B92: Value | C92: =VALUE(C95) -> 537
C93: =C95+0 -> 537
B94: Arguments
B95: Text | C95: 537
A104: Bonus: Bahttext
B105: Function
B106: BahtText | C106: =BAHTTEXT(C109) -> ยี่สิบเก้าบาทสามสิบห้าสตางค์
B108: Arguments
B109: Number | C109: 29.35

Sheet TextToColumns
C2: Fixed Width
C3: Delimited
A8: Fixed Width
A10: 123 1st Street | B10: Pittsburgh | C10: PA | D10: 15217
A11: 123 2nd Street | B11: New York | C11: NY | D11: 10011
A12: 123 3rd Street | B12: Philadephia | C12: PA | D12: 19104
A13: 123 4th Street | B13: Seattle | C13: WA | D13: 98101
A14: 123 5th Street | B14: Washington | C14: DC | D14: 20037
A15: 123 6th Street | B15: Charleston | C15: SC | D15: 29401
A16: 123 7th Street | B16: Des Moines | C16: IA | D16: 50309
A17: 123 8th Street | B17: Chicago | C17: IL | D17: 60614
A18: 123 9th Street | B18: Baltimore | C18: MD | D18: 21207
A19: 123 10th Street | B19: Minneapolis | C19: MN | D19: 55403
A20: 123 11th Street | B20: New Orleans | C20: LA | D20: 70112
A21: 123 12th Street | B21: Palm Springs | C21: CA | D21: 92264
... A25: 456 16th Street | B25: Burbank | C25: CA | D25: 91504
A48: Delimited
A50: Street Address | B50: City | C50: State | D50: ZIP
A51: 123 1st Street | B51: Pittsburgh | C51: PA | D51: 15217
A52: 123 2nd Street | B52: New York | C52: NY | D52: 10011
A53: 123 3rd Street | B53: Philadephia | C53: PA | D53: 19104
A54: 123 4th Street | B54: Seattle | C54: WA | D54: 98101
A55: 123 5th Street | B55: Washington | C55: DC | D55: 20037
A56: 123 6th Street | B56: Charleston | C56: SC | D56: 29401
A57: 123 7th Street | B57: Des Moines | C57: IA | D57: 50309
A58: 123 8th Street | B58: Chicago | C58: IL | D58: 60614
A59: 123 9th Street | B59: Baltimore | C59: MD | D59: 21207
A60: 123 10th Street | B60: Minneapolis | C60: MN | D60: 55403
A61: 123 11th Street | B61: New Orleans | C61: LA | D61: 70112
A62: 123 12th Street | B62: Palm Springs | C62: CA | D62: 92264
... A66: 456 16th Street | B66: Burbank | C66: CA | D66: 91504

Sheet RemoveDuplicates
A10: Employee | B10: Customer Name
A11: Andrew Cencini | B11: Company F
A12: Andrew Cencini | B12: Company F
A13: Andrew Cencini | B13: Company F
A14: Anne Hellung-Larsen | B14: Company BB
A15: Anne Hellung-Larsen | B15: Company Z
A16: Anne Hellung-Larsen | B16: Company Z
A17: Anne Hellung-Larsen | B17: Company Z
A18: Anne Hellung-Larsen | B18: Company Z
A19: Anne Hellung-Larsen | B19: Company AA
A20: Anne Hellung-Larsen | B20: Company Y
A21: Anne Hellung-Larsen | B21: Company Y
... A59: Robert Zare | B59: Company I

Sheet IF_And_Or
A7: IF Statements
A9: Name | B9: Knows Excel | C9: Knows Word | E9: Knows Excel | F9: Knows Word | H9: and | I9: or | J9: Knows Both | K9: Knows One
A10: Jen | B10: no | C10: No
A11: Alex | B11: no | C11: Yes
A12: Beth | B12: yes | C12: No
A13: Mike | B13: no | C13: Yes
A14: David | B14: no | C14: Yes
A15: Alison | B15: yes | C15: Yes
A16: Sarah | B16: no | C16: Yes
A17: Jessica | B17: yes | C17: No
A18: Roger | B18: yes | C18: No
A19: Eric | B19: yes | C19: Yes
A25: AND
B27: True if ALL conditions are true
B29: AND
B30: A | C30: B | D30: AND
B31: TRUE | C31: TRUE | D31: =AND(B31,C31) -> TRUE
B32: TRUE | C32: FALSE | D32: =AND(B32,C32) -> FALSE
B33: FALSE | C33: TRUE | D33: =AND(B33,C33) -> FALSE
B34: FALSE | C34: FALSE | D34: =AND(B34,C34) -> FALSE
A40: OR
B42: True if ONE of the conditions is true
B44: OR
B45: A | C45: B | D45: OR
B46: TRUE | C46: TRUE | D46: =OR(B46,C46) -> TRUE
B47: TRUE | C47: FALSE | D47: =OR(B47,C47) -> TRUE
B48: FALSE | C48: TRUE | D48: =OR(B48,C48) -> TRUE
B49: FALSE | C49: FALSE | D49: =OR(B49,C49) -> FALSE

Sheet Conditional Formatting
B1: Setting a Rule
B2: Managing Rules
B3: Data Bars
B4: Icon Sets
B5: Setting a Rule | C5: Managing Rules | D5: Data Bars | E5: Icon Sets
A7: Client Name | B7: Client Bill Rate (per hour) | C7: New Bill Rates
A8: Ernst & Old | B8: 150 | C8: 160 | D8: 160 | E8: 160
A9: Cost Liquidhome Coopers | B9: 100 | C9: 120 | D9: 120 | E9: 120
A10: GMPK Inc. | B10: 125 | C10: 130 | D10: 130 | E10: 130
A11: T&D Co. | B11: 175 | C11: 180 | D11: 180 | E11: 180
A12: Tiger Stearn | B12: 50 | C12: 70 | D12: 70 | E12: 70
A13: Leewoman Sisters | B13: 75 | C13: 80 | D13: 80 | E13: 80
A14: Acme Products | C14: 105 | D14: 105 | E14: 105
A15: Widgets Inc. | C15: 90 | D15: 90 | E15: 90
A16: Ok Homes and Gardens | C16: 60 | D16: 60 | E16: 60

Sheet Lookups
C2: xlookup
C3: vlookup
A10: Xlookup
A13: Company | B13: CONCORD FIRST ASSEMBLY
A14: Street Address | B14: =_xlfn.XLOOKUP(B13,RawData!A:A,RawData!B:B) -> 150 Warren Coleman Blvd
A15: State | B15: =_xlfn.XLOOKUP(B13,RawData!A:A,RawData!C:C) -> Concord
A16: Number of employees | B16: =_xlfn.XLOOKUP(B13,RawData!A:A,RawData!G:G) -> 255
A27: Xlookup
A29: Range_Lookup = True | B29: *Will Find closest match
A31: TestScore | B31: Grade
A32: 86 | B32: =_xlfn.XLOOKUP(A32,A37:A41,B37:B41,,-1) -> B
A37: 90 | B37: A
A38: 80 | B38: B
A39: 70 | B39: C
A40: 60 | B40: D
A41: 0 | B41: F
B52: Xlookup- multiple
C54: Number of employees
B55: BLOOMSBURG MILLS INC | C55: {=_xlfn.XLOOKUP(B55:B57,RawData!A:A,RawData!G:G)} -> 115
B56: CHAMPION LABORATORIES INC | C56: 300
B57: CLASSIC GRAPHICS INC | C57: 140
A67: Vlookup
A68: Range_Lookup = false | B68: * Must be an EXACT match
A70: Company | B70: AMESBURY GROUP INC
A71: Street Address | B71: =VLOOKUP(B70,RawData!A:G,2,FALSE) -> 159 Walker Rd
A72: State
A73: Number of employees
A84: Vlookup
A85: Range_Lookup = True | B85: *Will Find closest match
A87: TestScore | B87: Grade
A88: 90 | B88: =VLOOKUP(A88,A93:B97,2,TRUE) -> A
A92: Grading Scale
A93: 0 | B93: F
A94: 60 | B94: D
A95: 70 | B95: C
A96: 80 | B96: B
A97: 90 | B97: A
A336: Employee Table
A338: Company | B338: NumberOfEmployees
A339: ABAC/AMERICAN IMC INC | B339: 200
A340: AEROTEK | B340: 680
A341: AFFINIA GROUP INC | B341: 1389
A342: ARROW HOME FASHIONS | B342: 111
A343: ARVIN MERITOR INC | B343: 350
A344: ATI ALLVAC | B344: 160
A345: BARLOWORLD HANDLING LP | B345: 187
A346: BESAM AUTOMATED ENTRANCE SYSTEMS | B346: 100
A347: BOWERS FIBERS INC | B347: 100
A348: BROOKS EQUIPMENT CO INC | B348: 115
A349: CABARRUS HEALTH ALLIANCE | B349: 250
A350: CANTEEN VENDING SERVICES | B350: 243
... A437: ZENITH FREIGHT LINES LLC | B437: 150

Sheet Index Match
C2: Array
C3: Index
C4: Match
C5: Index-Match
A10: Index
A12: Array | B12: Table or row to index
A13: Row | B13: Row of data | E13: Color | F13: Monday | G13: Tuesday | H13: Wednesday | I13: Thursday | J13: Friday
A14: Column | B14: Column of data | D14: Apple | E14: Red | F14: 15 | G14: 11 | H14: 23 | I14: 22 | J14: 20
D15: Pear | E15: Green | F15: 16 | G15: 23 | H15: 13 | I15: 13 | J15: 12
A16: =INDEX(D13:J16,3,5) -> 13 | D16: Banana | E16: Yellow | F16: 10 | G16: 12 | H16: 18 | I16: 16 | J16: 13
A22: Match
A24: LookupValue | B24: Value to look up | E24: Color | F24: Monday | G24: Tuesday | H24: Wednesday | I24: Thursday | J24: Friday
A25: LookupArray | B25: Group of cells to do the lookup | D25: Apple | E25: Red | F25: 15 | G25: 11 | H25: 23 | I25: 22 | J25: 20
A26: MatchType | B26: -1-Less Than, 0-Equal,1-Greater Than | D26: Pear | E26: Green | F26: 16 | G26: 23 | H26: 13 | I26: 13 | J26: 12
D27: Banana | E27: Yellow | F27: 10 | G27: 12 | H27: 18 | I27: 16 | J27: 13
A28: =MATCH(B28,D24:D27,0) -> 3 | B28: Pear
A29: =MATCH(B29,E24:E27,0) -> 3 | B29: Green
A30: =MATCH(B30,D24:J24,0) -> 5 | B30: Wednesday
A34: Put Them Together
E35: Color | F35: Monday | G35: Tuesday | H35: Wednesday | I35: Thursday | J35: Friday
A36: =INDEX(D35:J38,MATCH(B36,D35:D38,0),MATCH(B37,D35:J35,0)) -> 12 | B36: Pear | D36: Apple | E36: Red | F36: 15 | G36: 11 | H36: 23 | I36: 22 | J36: 20
B37: Friday | D37: Pear | E37: Green | F37: 16 | G37: 23 | H37: 13 | I37: 13 | J37: 12
D38: Banana | E38: Yellow | F38: 10 | G38: 12 | H38: 18 | I38: 16 | J38: 13
A39: =INDEX(D35:J38,MATCH(B39,E35:E38,0),MATCH(B40,D35:J35,0)) -> 16 | B39: Yellow
B40: Thursday
A255: Employee Table
A257: Company | B257: NumberOfEmployees
A258: ABAC/AMERICAN IMC INC | B258: 200
A259: AEROTEK | B259: 680
A260: AFFINIA GROUP INC | B260: 1389
A261: ARROW HOME FASHIONS | B261: 111
A262: ARVIN MERITOR INC | B262: 350
A263: ATI ALLVAC | B263: 160
A264: BARLOWORLD HANDLING LP | B264: 187
A265: BESAM AUTOMATED ENTRANCE SYSTEMS | B265: 100
A266: BOWERS FIBERS INC | B266: 100
A267: BROOKS EQUIPMENT CO INC | B267: 115
A268: CABARRUS HEALTH ALLIANCE | B268: 250
A269: CANTEEN VENDING SERVICES | B269: 243
... A356: ZENITH FREIGHT LINES LLC | B356: 150

Sheet RawData
A1: Company | B1: MailAddress | C1: MailCity | D1: MailSt | E1: MailZip | F1: County | G1: NumberOfEmployees
A2: AAA COOPER TRANSPORTATION CO INC | B2: 4000 Sam Wilson Rd | C2: Charlotte | D2: NC | E2: 28269 | F2: Mecklenburg | G2: 150
A3: AB CARTER INC | B3: PO Box 518 | C3: Gastonia | D3: NC | E3: 28053 | F3: Gaston | G3: 140
A4: ABAC/AMERICAN IMC INC | B4: 1623 Cedar Line Dr | C4: Rock Hill | D4: SC | E4: 29730 | F4: York | G4: 200
A5: ABERCROMBIE & FITCH CO | B5: 6301 Fitch Path | C5: New Albany | D5: OH | E5: 43054 | F5: Regional | G5: 240
A6: ABM LANDSCAPE SERVICES | B6: 11301 Reames Rd | C6: Charlotte | D6: NC | E6: 28269 | F6: Mecklenburg | G6: 100
A7: ACCUMA CORP | B7: 133 Fanjoy Rd | C7: Statesville | D7: NC | E7: 28625 | F7: Iredell | G7: 120
A8: ACCURATE STAFFING CONSULTANTS INC | B8: 13000 York Rd, Box 312 | C8: Charlotte | D8: NC | E8: 28625 | F8: Mecklenburg | G8: 100
A9: ACE HARDWARE | B9: 2200 Kensington Ct | C9: Oak Brook | D9: IL | E9: 60523 | F9: Regional | G9: 210
A10: ACOSTA SALES & MARKETING | B10: PO Box 34309 | C10: Charlotte | D10: NC | E10: 28234 | F10: Mecklenburg | G10: 200
A11: ACOUSTICS INC | B11: PO Box 242507 | C11: Charlotte | D11: NC | E11: 28224 | F11: Mecklenburg | G11: 150
A12: ACTAVIS MID ATLANTIC LLC | B12: 1877 Kawai Rd | C12: Lincolnton | D12: NC | E12: 28092 | F12: Lincoln | G12: 180
A13: ACTION PERSONNEL SERVICES | B13: 654 Pressley Rd | C13: Charlotte | D13: NC | E13: 28217 | F13: Mecklenburg | G13: 250
A14: ADECCO | B14: 8520 Cliff Cameron Dr, Suite 170 | C14: Charlotte | D14: NC | E14: 28268 | F14: Regional | G14: 5000
A15: ADESA CHARLOTTE | B15: PO Box 411168 | C15: Charlotte | D15: NC | E15: 28241 | F15: Mecklenburg | G15: 300
A16: ADMARK GRAPHIC SYSTEMS INC | B16: 9700 Metromont Industrial Blvd | C16: Charlotte | D16: NC | E16: 28269 | F16: Mecklenburg | G16: 100
A17: ADP INC | B17: 201 Regency Executive Park Dr | C17: Charlotte | D17: NC | E17: 28217 | F17: Mecklenburg | G17: 200
A18: ADVANCED IMAGING SYSTEMS INC | B18: 10617 Southern Loop Blvd | C18: Pineville | D18: NC | E18: 28134 | F18: Mecklenburg | G18: 100
A19: AEP INDUSTRIES INC | B19: 303 Seaboard Dr | C19: Matthews | D19: NC | E19: 28104 | F19: Mecklenburg | G19: 283
A20: AEROTEK | B20: 2359 Perimeter Point Pkwy, Suite 200 | C20: Charlotte | D20: NC | E20: 28208 | F20: Mecklenburg | G20: 680
... A145: BOBCATS BASKETBALL LLC | B145: 129 W Trade St, Suite 700 | C145: Charlotte | D145: NC | E145: 28202 | F145: Mecklenburg | G145: 204
A146: BOGGS PAVING | B146: PO Box 1609 | C146: Monroe | D146: NC | E146: 28111 | F146: Union | G146: 300
A147: BOJANGLES' RESTAURANTS INC | B147: PO Box 240239 | C147: Charlotte | D147: NC | E147: 28224 | F147: Regional | G147: 1800
A148: BONDED LOGISTICS INC | B148: PO Box 480203 | C148: Charlotte | D148: NC | E148: 28269 | F148: Mecklenburg | G148: 100
A149: BONITZ FLOORING GROUP | B149: 4539 Enterprise Dr NW | C149: Concord | D149: NC | E149: 28027 | F149: Cabarrus | G149: 260
A150: BORAL BRICKS INC | B150: PO Box 1249 | C150: Salisbury | D150: NC | E150: 28145 | F150: Rowan | G150: 130
A151: BORAL BRICKS INC, VAN WYCK PLANT | B151: PO Box 99 | C151: Van Wyck | D151: SC | E151: 29744 | F151: Lancaster | G151: 100
A152: BORDERS GROUP INC | B152: 100 Phoenix Dr | C152: Ann Arbor | D152: MI | E152: 48108 | F152: Regional | G152: 210
A153: BOSCH REXROTH CORP | B153: 14001 S Lakes Dr | C153: Charlotte | D153: NC | E153: 28273 | F153: Mecklenburg | G153: 150
A154: BOSTON GEAR | B154: 701 Carrier Dr | C154: Charlotte | D154: NC | E154: 28216 | F154: Mecklenburg | G154: 180
A155: BOVIS LEND LEASE | B155: 2550 W Tyvola Rd, Suite 600 | C155: Charlotte | D155: NC | E155: 28217 | F155: Mecklenburg | G155: 254
A156: BOWATER INC | B156: PO Box 7 | C156: Catawba | D156: SC | E156: 29704 | F156: York | G156: 1040
A157: BOWERS FIBERS INC | B157: 4001 Yancey Rd | C157: Charlotte | D157: NC | E157: 28217 | F157: Mecklenburg | G157: 100
A158: BOY SCOUTS OF AMERICA | B158: PO Box 7143 | C158: Charlotte | D158: NC | E158: 28241 | F158: Mecklenburg | G158: 185
... A226: CAROLINA ROOFING INC | B226: 1726 Riverview Rd | C226: Lincolnton | D226: NC | E226: 28092 | F226: Lincoln | G226: 350
A227: CAROLINA STALITE/JOHNSON CONCRETE | B227: PO Box 1037 | C227: Salisbury | D227: NC | E227: 28145 | F227: Rowan | G227: 110
A228: CAROLINA STEEL & STONE INC | B228: 9925 Metromont Industrial Blvd | C228: Charlotte | D228: NC | E228: 28269 | F228: Mecklenburg | G228: 150
A229: CAROLINAS HEALTHCARE SYSTEM | B229: PO Box 32861 | C229: Charlotte | D229: NC | E229: 28232 | F229: Regional | G229: 26283
A230: CAROLINAS SPECIALTY HOSPITAL | B230: 2001 Vail Ave, 7th Floor S | C230: Charlotte | D230: NC | E230: 28207 | F230: Mecklenburg | G230: 130
A231: CAROLINAS UNION HEALTHCARE | B231: PO Box 633 | C231: Monroe | D231: NC | E231: 28111 | F231: Union | G231: 115
A232: CAROMONT HEALTH INC | B232: PO Box 1747 | C232: Gastonia | D232: NC | E232: 28053 | F232: Gaston | G232: 3230
A233: CAROTEK INC | B233: PO Box 1395 | C233: Matthews | D233: NC | E233: 28106 | F233: Mecklenburg | G233: 105
A234: CARPENTER CO | B234: PO Box 455 | C234: Taylorsville | D234: NC | E234: 28681 | F234: Alexander | G234: 100
A235: CARPENTER CO | B235: PO Box 879 | C235: Conover | D235: NC | E235: 28613 | F235: Regional | G235: 380
A236: CARPENTER DECORATING CO INC | B236: PO Box 2027 | C236: Hickory | D236: NC | E236: 28603 | F236: Catawba | G236: 100
A237: CARPENTER INDUSTRIES | B237: 4140 Concord Pkwy S | C237: Concord | D237: NC | E237: 28027 | F237: Cabarrus | G237: 130
A238: CARRABBA'S ITALIAN GRILL INC | B238: 405 N Reo St | C238: Tampa | D238: FL | E238: 33609 | F238: Regional | G238: 350
A239: CARREKER CORP | B239: 10926 David Taylor Dr, Suite 200 | C239: Charlotte | D239: NC | E239: 28262 | F239: Mecklenburg | G239: 100
... A251: CATO CORP, THE | B251: PO Box 34216 | C251: Charlotte | D251: NC | E251: 28234 | F251: Regional | G251: 600
A252: CBRL GROUP INC | B252: PO Box 787 | C252: Lebanon | D252: TN | E252: 37088 | F252: Regional | G252: 250
A253: CBS RADIO SALES INC | B253: 1520 South Blvd, Suite 300 | C253: Charlotte | D253: NC | E253: 28203 | F253: Mecklenburg | G253: 130
A254: CCL LABEL INC | B254: 4000 Westinghouse Blvd | C254: Charlotte | D254: NC | E254: 28273 | F254: Mecklenburg | G254: 115
A255: CELESTICA | B255: 7345 IBM Dr | C255: Charlotte | D255: NC | E255: 28262 | F255: Mecklenburg | G255: 243
A256: CEM CORP | B256: PO Box 200 | C256: Matthews | D256: NC | E256: 28106 | F256: Union | G256: 150
A257: CENTEX HOMES | B257: 4235 S Stream Blvd, Suite 400 | C257: Charlotte | D257: NC | E257: 28220 | F257: Mecklenburg | G257: 165
A258: CENTRAL PIEDMONT COMMUNITY COLLEGE | B258: PO Box 35009 | C258: Charlotte | D258: NC | E258: 28235 | F258: Mecklenburg | G258: 2053
A259: CENTRO INC | B259: 2725 Kelly Blvd | C259: Claremont | D259: NC | E259: 28610 | F259: Catawba | G259: 154
A260: CENTURY 21 HECHT REALTY INC | B260: 885 N Hwy 16 | C260: Denver | D260: NC | E260: 28037 | F260: Lincoln | G260: 126
A261: CENTURY CONTRACTORS INC | B261: 5100 Smith Farm Rd | C261: Matthews | D261: NC | E261: 28104 | F261: Mecklenburg | G261: 250
A262: CENTURY FURNITURE INDUSTRIES | B262: PO Box 608 | C262: Hickory | D262: NC | E262: 28603 | F262: Regional | G262: 2100
A263: CHAMPION LABORATORIES INC | B263: 200 Ratchford Rd | C263: York | D263: SC | E263: 29745 | F263: York | G263: 300
A264: CHARLOTTE CARDIOLOGY ASSOCIATES PA | B264: 309 S Sharon Amity Rd, Suite 200 | C264: Charlotte | D264: NC | E264: 28211 | F264: Mecklenburg | G264: 112
... A311: CITY OF KINGS MOUNTAIN | B311: PO Box 429 | C311: Kings Mountain | D311: NC | E311: 28086 | F311: Cleveland | G311: 188
A312: CITY OF LANCASTER | B312: PO Box 1149 | C312: Lancaster | D312: SC | E312: 29721 | F312: Lancaster | G312: 155
A313: CITY OF LINCOLNTON | B313: PO Box 617 | C313: Lincolnton | D313: NC | E313: 28093 | F313: Lincoln | G313: 143
A314: CITY OF MONROE | B314: PO Box 69 | C314: Monroe | D314: NC | E314: 28111 | F314: Union | G314: 650
A315: CITY OF MOUNT HOLLY | B315: PO Box 406 | C315: Mount Holly | D315: NC | E315: 28120 | F315: Gaston | G315: 153
A316: CITY OF NEWTON | B316: PO Box 550 | C316: Newton | D316: NC | E316: 28658 | F316: Catawba | G316: 245
A317: CITY OF ROCK HILL | B317: PO Box 11706 | C317: Rock Hill | D317: SC | E317: 29731 | F317: York | G317: 800
A318: CITY OF SALISBURY | B318: PO Box 479 | C318: Salisbury | D318: NC | E318: 28145 | F318: Rowan | G318: 461
A319: CITY OF SHELBY | B319: PO Box 207 | C319: Shelby | D319: NC | E319: 28151 | F319: Cleveland | G319: 360
A320: CITY OF STATESVILLE | B320: PO Box 1111 | C320: Statesville | D320: NC | E320: 28687 | F320: Iredell | G320: 375
A321: CITY OF YORK | B321: 10 N Roosevelt St | C321: York | D321: SC | E321: 29745 | F321: York | G321: 100
A322: CLARIANT CORP USA | B322: 4000 Monroe Rd | C322: Charlotte | D322: NC | E322: 28205 | F322: Regional | G322: 500
A323: CLARKE AMERICAN CHECKS INC | B323: 9711 David Taylor Dr | C323: Charlotte | D323: NC | E323: 28262 | F323: Mecklenburg | G323: 100
A324: CLASSIC GRAPHICS INC | B324: PO Box 480127 | C324: Charlotte | D324: NC | E324: 28269 | F324: Mecklenburg | G324: 140
... A382: CROSLAND INC | B382: 227 W Trade St, Suite 800 | C382: Charlotte | D382: NC | E382: 28202 | F382: Mecklenburg | G382: 150
A383: CROWDER CONSTRUCTION CO | B383: PO Box 30007 | C383: Charlotte | D383: NC | E383: 28230 | F383: Mecklenburg | G383: 300
A384: CROWN BEVERAGE PACKAGING | B384: PO Box 759 | C384: Cheraw | D384: SC | E384: 29520 | F384: Chesterfield | G384: 184
A385: CROWN HONDA OF CHARLOTTE | B385: 7001 E Independence Blvd | C385: Charlotte | D385: NC | E385: 28227 | F385: Mecklenburg | G385: 100
A386: CSA LLC | B386: 128 Speedway Dr | C386: Mooresville | D386: NC | E386: 28117 | F386: Iredell | G386: 150
A387: CT COMMUNICATIONS INC | B387: PO Box 227 | C387: Concord | D387: NC | E387: 28026 | F387: Cabarrus | G387: 650
A388: CT GROUP | B388: PO Box 339 | C388: Claremont | D388: NC | E388: 28610 | F388: Catawba | G388: 500
A389: CTX BUILDERS SUPPLY | B389: 2100 Sterling Dr | C389: Albemarle | D389: NC | E389: 28001 | F389: Stanly | G389: 100
A390: CULP BROTHERS INC | B390: 3300 Bethlehem Church Rd | C390: Gold Hill | D390: NC | E390: 28071 | F390: Rowan | G390: 100
A391: CUMMINS ATLANTIC INC | B391: PO Box 7787 | C391: Charlotte | D391: NC | E391: 28241 | F391: Regional | G391: 120
A392: CUMULUS FIBERS INC | B392: 1101 Tarhill Rd | C392: Charlotte | D392: NC | E392: 28208 | F392: Mecklenburg | G392: 100
A393: CURTISS-WRIGHT CONTROLS INC | B393: 15800 John J Delaney Dr, Suite 200 | C393: Charlotte | D393: NC | E393: 28277 | F393: Regional | G393: 280
A394: CURVES | B394: 2910G Mount Holly-Huntersville Rd | C394: Charlotte | D394: NC | E394: 28214 | F394: Regional | G394: 220
A395: CUSTOM GLASS PRODUCTS | B395: PO Box 1249 | C395: Salisbury | D395: NC | E395: 28145 | F395: Rowan | G395: 150
... A403: DANAHER TOOL GROUP | B403: 1228 Isley Dr | C403: Gastonia | D403: NC | E403: 28053 | F403: Gaston | G403: 500
A404: DARDEN RESTAURANTS INC | B404: PO Box 593330 | C404: Orlando | D404: FL | E404: 32859 | F404: Regional | G404: 500
A405: DAVE AND BUSTER'S | B405: 8361 Concord Mills Blvd | C405: Concord | D405: NC | E405: 28207 | F405: Cabarrus | G405: 150
A406: DAVEY TREE EXPERT CO | B406: 6039 McDaniel Ln | C406: Charlotte | D406: NC | E406: 28213 | F406: Mecklenburg | G406: 120
A407: DAVIDSON COLLEGE | B407: PO Box 7163 | C407: Davidson | D407: NC | E407: 28035 | F407: Mecklenburg | G407: 800
A408: DAVIS REGIONAL MEDICAL CENTER | B408: PO Box 1823 | C408: Statesville | D408: NC | E408: 28687 | F408: Iredell | G408: 600
A409: DAVIS STEEL & IRON CO INC | B409: 1035 Commercial Dr | C409: Matthews | D409: NC | E409: 28104 | F409: Mecklenburg | G409: 100
A410: DEAN AND DELUCA | B410: 560 Broadway | C410: New York | D410: NY | E410: 10012 | F410: Regional | G410: 100
A411: DECORE-ATIVE SPECIALTIES | B411: 701 Industrial Dr | C411: Monroe | D411: NC | E411: 28110 | F411: Union | G411: 120
A412: DELHAIZE AMERICA INC/FOOD LION LLC | B412: PO Box 1330 | C412: Salisbury | D412: NC | E412: 28145 | F412: Regional | G412: 8658
...
